MANIFEST.in
requirements.txt
setup.py
vialink/utils/datafetcher/__init__.py
vialink/utils/datafetcher/retrieve_data.py
vialink/utils/datafetcher/settings.py
vialink/utils/datafetcher/upload_data.py
vialink/utils/datafetcher/utils.py
vialink_utils_datafetcher.egg-info/PKG-INFO
vialink_utils_datafetcher.egg-info/SOURCES.txt
vialink_utils_datafetcher.egg-info/dependency_links.txt
vialink_utils_datafetcher.egg-info/requires.txt
vialink_utils_datafetcher.egg-info/top_level.txt