Metadata-Version: 2.1
Name: vialink-utils-datafetcher
Version: 0.0.3
Summary: Vialink Utils
Home-page: UNKNOWN
Author: SSripilaipong
Author-email: santhapon@via.link
License: Apache 2.0
Platform: UNKNOWN
Requires-Python: >=3.7
